{
	"openBrewVersion": "1.0.0",
	"encoding": "UTF-8",
	"info": {
		"recipeName": "Schwabacher Herbstgold Hefeweizen",
		"recipeVersion": 1,
		"beerType": "Helles Hefeweizen",
		"recipeDescription": [
			{
				"language": "en",
				"text": "This great beer must be brewed with passion. Otherwise it won't taste good."
			}
		],
		"author": {
			"breweryName": "holdmybeer"
		}
	},
	"vitalStatistics": {
		"expectedEfficiency": {
			"amount": 62,
			"relativeUnit": "percent"
		},
		"expectedOriginalGravity": {
			"amount": 13.85,
			"ratioUnit": "degreePlato"
		},
		"alcoholContent": {
			"amount": 6.3,
			"ratioUnit": "volumePercent"
		},
		"bitterness": {
			"amount": 15,
			"tasteUnit": "ibu"
		},
		"color": {
			"amount": 11.3,
			"colorUnit": "ebc"
		}
	},
	"brew": {
		"mash": {
			"mashWater": {
				"water": {
					"amount": 23,
					"volumeUnit": "liter"
				}
			},
			"solids": [
				{
					"name": "Weizenmalz",
					"type": "grain",
					"portion": {
						"amount": 2250.0,
						"weightUnit": "grams"
					}
				},
				{
					"name": "Pilsener Malz",
					"type": "grain",
					"portion": {
						"amount": 2750.0,
						"weightUnit": "grams"
					}
				},
				{
					"name": "Karamell Malz",
					"type": "grain",
					"portion": {
						"amount": 200.0,
						"weightUnit": "grams"
					}
				}
			],
			"rests": [
				{
					"name": "Einmaischen",
					"targetTemperature": {
						"amount": 47,
						"tempUnit": "celsius"
					},
					"restingTime": {
						"amount": 2,
						"timeUnit": "minutes"
					}
				},
				{
					"name": "Maltoserast",
					"targetTemperature": {
						"amount": 62,
						"tempUnit": "celsius"
					},
					"restingTime": {
						"amount": 20,
						"timeUnit": "minutes"
					}
				},
				{
					"name": "Verzuckerungsrast 1",
					"targetTemperature": {
						"amount": 68,
						"tempUnit": "celsius"
					},
					"restingTime": {
						"amount": 25,
						"timeUnit": "minutes"
					}
				},
				{
					"name": "Verzuckerungsrast 2",
					"targetTemperature": {
						"amount": 72,
						"tempUnit": "celsius"
					},
					"restingTime": {
						"amount": 30,
						"timeUnit": "minutes"
					}
				},
				{
					"name": "Abmaischen",
					"targetTemperature": {
						"amount": 80,
						"tempUnit": "celsius"
					},
					"restingTime": {
						"amount": 1,
						"timeUnit": "minutes"
					}
				}
			]
		},
		"lauter": {
			"restingTime": {
				"amount": 20,
				"timeUnit": "minutes"
			},
			"spargeWater": {
				"water": {
					"amount": 23,
					"volumeUnit": "liter"
				},
				"targetTemperature": {
					"amount": 80,
					"tempUnit": "celsius"
				}
			}
		},
		"boil": {
			"overallBoilTime": {
				"amount": 90,
				"timeUnit": "minutes"
			},
			"hops": [
				{
					"name": "Hallertau Magnum",
					"alphaAcid": {
						"amount": 12.1,
						"chemicalUnit": "alphaAcid"
					},
					"type": "bitter",
					"use": "boil",
					"time": {
						"amount": 10,
						"timeUnit": "minutes"
					}
				},
				{
					"name": "Hallertau Saphir",
					"alphaAcid": {
						"amount": 4.1,
						"chemicalUnit": "alphaAcid"
					},
					"type": "aroma",
					"use": "boil",
					"time": {
						"amount": 10,
						"timeUnit": "minutes"
					}
				}
			]
		},
		"fermentation": {
			"yeast": {
				"yeastName": "Safale WB40",
				"yeastType": "top-fermented",
				"yeastAmount": {
					"amount": 11,
					"weightUnit": "grams"
				}
			},
			"targetTemperature": {
				"amount": 19,
				"tempUnit": "celsius"
			}
		}
	}
}